type_stripper/__init__.py
type_stripper-0.1.5.dist-info/METADATA
type_stripper-0.1.5.dist-info/WHEEL
type_stripper-0.1.5.dist-info/entry_points.txt
type_stripper-0.1.5.dist-info/licenses/LICENSE
type_stripper-0.1.5.dist-info/RECORD
