Metadata-Version: 2.4
Name: type-stripper
Version: 0.1.5
Summary: A CLI tool that removes type annotations from Python source files.
Project-URL: homepage, https://github.com/griceturrble/python-type-stripper
Author-email: Galen Rice <griceturrble@protonmail.com>
License-File: LICENSE
Keywords: transpiler,typing
Classifier: Development Status :: 3 - Alpha
Classifier: Intended Audience :: Developers
Classifier: License :: OSI Approved :: Apache Software License
Classifier: Programming Language :: Python :: 3
Classifier: Programming Language :: Python :: 3.9
Classifier: Programming Language :: Python :: 3.10
Classifier: Programming Language :: Python :: 3.11
Classifier: Programming Language :: Python :: 3.12
Classifier: Programming Language :: Python :: 3.13
Classifier: Topic :: Software Development :: Build Tools
Requires-Python: >=3.9
Requires-Dist: click>=8.1.8
Requires-Dist: libcst>=1.5.1
